datanba/__init__.py
datanba/player_stats.py
python_nba_pack/__init__.py
python_nba_pack/player_stats.py
nba_player-0.6.8.dist-info/LICENSE
nba_player-0.6.8.dist-info/METADATA
nba_player-0.6.8.dist-info/WHEEL
nba_player-0.6.8.dist-info/top_level.txt
nba_player-0.6.8.dist-info/RECORD
