Metadata-Version: 2.1
Name: nba-player
Version: 0.6.8
Summary: Get all NBA player data into JSON format
Home-page: https://github.com/avyayv/python_nba_players
Author: Avyay Varadarajan
Author-email: avyayv@gmail.com
License: UNKNOWN
Platform: UNKNOWN
Classifier: Programming Language :: Python :: 3
Classifier: License :: OSI Approved :: MIT License
Classifier: Operating System :: OS Independent
